settingsclass/__init__.py
settingsclass/localizer.py
settingsclass/settingsclass.py
settingsclass/loc/settings.csv
settingsclass-0.1.5.dist-info/licenses/LICENSE
settingsclass-0.1.5.dist-info/METADATA
settingsclass-0.1.5.dist-info/WHEEL
settingsclass-0.1.5.dist-info/top_level.txt
settingsclass-0.1.5.dist-info/RECORD
