Metadata-Version: 2.4
Name: settingsclass
Version: 0.1.5
Summary: A class decorator for easily storing setting values, with automatic sync to disk
Author: Robert Kajnak
License: MIT Licence
Project-URL: Homepage, https://github.com/id-ai-labo/settingsclass
Keywords: settings,config,configuration,ini,configparser,dataclass
Classifier: Programming Language :: Python
Requires-Python: >=3.11
License-File: LICENSE
Requires-Dist: loguru
Requires-Dist: pycryptodome>=3.20.0
Dynamic: license-file
